tiny_cpu/stack.v
module stack (
    input clk, reset, load, push, pop,
    input [15:0] d,
    output reg [15:0] qtop,
    output reg [15:0] qnext
);
    reg [15:0] stack_mem [0:15]; // 16-depth stack
    reg [3:0] sp; // Stack pointer (4-bit for 16-depth stack)

    always @(posedge clk or posedge reset) begin
        if (reset) begin
            sp <= 4'b0;
            qtop <= 16'b0;
            qnext <= 16'b0;
        end else begin
            if (push && sp < 15) begin
                stack_mem[sp] <= d;
                sp <= sp + 1;
            end

            if (pop && sp > 0) begin
                sp <= sp - 1;
            end

            if (sp > 0) begin
                qtop <= stack_mem[sp - 1];
            end else begin
                qtop <= 16'b0; // Default value when stack is empty
            end

            if (sp > 1) begin
                qnext <= stack_mem[sp - 2];
            end else begin
                qnext <= 16'b0;
            end
        end
    end
endmodule

stack/stack_tb.v
`timescale 1ns / 1ps

module stack_tb;
    reg clk, reset, load, push, pop;
    reg [15:0] d;
    wire [15:0] qtop, qnext;

    // Instantiate the stack module
    stack uut (
        .clk(clk),
        .reset(reset),
        .load(load),
        .push(push),
        .pop(pop),
        .d(d),
        .qtop(qtop),
        .qnext(qnext)
    );

    // Generate clock signal
    always #10 clk = ~clk; // 20ns period (50MHz)

    initial begin
        $dumpfile("stack_tb.vcd");
        $dumpvars(0, stack_tb);

        // Initialize signals
        clk = 0;
        reset = 1;
        load = 0;
        push = 0;
        pop = 0;
        d = 16'b0;

        // Apply Reset
        #20 reset = 0;
        #20 reset = 1; // Ensure reset is applied
        #20 reset = 0;

        // Push 3 values onto stack
        #20 d = 16'hAAAA; push = 1; #20 push = 0;
        #20 d = 16'hBBBB; push = 1; #20 push = 0;
        #20 d = 16'hCCCC; push = 1; #20 push = 0;

        // Pop 2 values from stack
        #20 pop = 1; #20 pop = 0;
        #20 pop = 1; #20 pop = 0;

        // Try popping beyond stack limit (should handle gracefully)
        #20 pop = 1; #20 pop = 0;
        #20 pop = 1; #20 pop = 0;

        // Push more values to test
        #20 d = 16'hDDDD; push = 1; #20 push = 0;
        #20 d = 16'hEEEE; push = 1; #20 push = 0;

        #100 $finish;
    end
endmodule

stack/stack.sim/sim_1/behav/xsim/stack_tb.vcd
$date
   Tue Mar 25 14:49:07 2025
$end

$version
  2024.1
  $dumpfile ("stack_tb.vcd") 
$end

$timescale
  1ps
$end

$scope module stack_tb $end
$var reg 1 ! clk $end
$var reg 1 " reset $end
$var reg 1 # load $end
$var reg 1 $ push $end
$var reg 1 % pop $end
$var reg 16 & d [15:0] $end
$var wire 16 ' qtop [15:0] $end
$var wire 16 ( qnext [15:0] $end
$scope module uut $end
$var wire 1 ) clk $end
$var wire 1 * reset $end
$var wire 1 + load $end
$var wire 1 , push $end
$var wire 1 - pop $end
$var wire 16 . d [15:0] $end
$var reg 16 / qtop [15:0] $end
$var reg 16 0 qnext [15:0] $end
$var reg 4 1 sp [3:0] $end
$upscope $end
$upscope $end
$enddefinitions $end

#0
$dumpvars
0!
1"
0#
0$
0%
b0 &
b0 '
b0 (
0)
1*
0+
0,
0-
b0 .
b0 /
b0 0
b0 1
$end

#10000
1!
1)

#20000
0!
0"
0)
0*

#30000
1!
1)

#40000
0!
1"
0)
1*

#50000
1!
1)

#60000
0!
0"
0)
0*

#70000
1!
1)

#80000
0!
1$
b1010101010101010 &
0)
1,
b1010101010101010 .

#90000
1!
1)
b1 1

#100000
0!
0$
0)
0,

#110000
1!
b1010101010101010 '
1)
b1010101010101010 /

#120000
0!
1$
b1011101110111011 &
0)
1,
b1011101110111011 .

#130000
1!
1)
b10 1

#140000
0!
0$
0)
0,

#150000
1!
b1011101110111011 '
b1010101010101010 (
1)
b1011101110111011 /
b1010101010101010 0

#160000
0!
1$
b1100110011001100 &
0)
1,
b1100110011001100 .

#170000
1!
1)
b11 1

#180000
0!
0$
0)
0,

#190000
1!
b1100110011001100 '
b1011101110111011 (
1)
b1100110011001100 /
b1011101110111011 0

#200000
0!
1%
0)
1-

#210000
1!
1)
b10 1

#220000
0!
0%
0)
0-

#230000
1!
b1011101110111011 '
b1010101010101010 (
1)
b1011101110111011 /
b1010101010101010 0

#240000
0!
1%
0)
1-

#250000
1!
1)
b1 1

#260000
0!
0%
0)
0-

#270000
1!
b1010101010101010 '
b0 (
1)
b1010101010101010 /
b0 0

#280000
0!
1%
0)
1-

#290000
1!
1)
b0 1

#300000
0!
0%
0)
0-

#310000
1!
b0 '
1)
b0 /

#320000
0!
1%
0)
1-

#330000
1!
1)

#340000
0!
0%
0)
0-

#350000
1!
1)

#360000
0!
1$
b1101110111011101 &
0)
1,
b1101110111011101 .

#370000
1!
1)
b1 1

#380000
0!
0$
0)
0,

#390000
1!
b1101110111011101 '
1)
b1101110111011101 /

#400000
0!
1$
b1110111011101110 &
0)
1,
b1110111011101110 .

#410000
1!
1)
b10 1

#420000
0!
0$
0)
0,

#430000
1!
b1110111011101110 '
b1101110111011101 (
1)
b1110111011101110 /
b1101110111011101 0

